helpers/__init__.py
helpers-0.2.0.dist-info/LICENSE
helpers-0.2.0.dist-info/METADATA
helpers-0.2.0.dist-info/WHEEL
helpers-0.2.0.dist-info/top_level.txt
helpers-0.2.0.dist-info/RECORD
